MainShortcuts2/__init__.py
MainShortcuts2/__main__.py
MainShortcuts2/_any2json_regs.py
MainShortcuts2/_module_info.py
MainShortcuts2/_ms2app_regs.py
MainShortcuts2/advanced.py
MainShortcuts2/any2json.py
MainShortcuts2/api/base.py
MainShortcuts2/api/gigachat.py
MainShortcuts2/api/russian_trusted_root_ca_pem.crt
MainShortcuts2/api/russian_trusted_sub_ca_pem.crt
MainShortcuts2/api/webdav.py
MainShortcuts2/cfg.py
MainShortcuts2/core.py
MainShortcuts2/core_config.py
MainShortcuts2/dict.py
MainShortcuts2/dir.py
MainShortcuts2/file.py
MainShortcuts2/json.py
MainShortcuts2/linux.py
MainShortcuts2/list.py
MainShortcuts2/ms2app.py
MainShortcuts2/ms2hash.py
MainShortcuts2/path.py
MainShortcuts2/proc.py
MainShortcuts2/regex.py
MainShortcuts2/special_chars.py
MainShortcuts2/sql/_sql_base.py
MainShortcuts2/sql/postgresql.py
MainShortcuts2/sql/sqlite.py
MainShortcuts2/str.py
MainShortcuts2/term.py
MainShortcuts2/types.py
MainShortcuts2/utils.py
MainShortcuts2/win.py
mainshortcuts2-2.6.5.dist-info/METADATA
mainshortcuts2-2.6.5.dist-info/WHEEL
mainshortcuts2-2.6.5.dist-info/entry_points.txt
mainshortcuts2-2.6.5.dist-info/RECORD
